{
  "CLIENT_001": {
    "client_id": "CLIENT_001",
    "name": "Default Trading Client",
    "pan_number": "ABCDE1234F",
    "aadhaar_number": "123456789012",
    "date_of_birth": "1990-01-01",
    "address": "123 Compliance Street, Mumbai, IN",
    "phone": "9876543210",
    "email": "client@example.com",
    "kyc_status": "verified",
    "verification_date": "2024-01-01T09:00:00",
    "verified_by": "ComplianceBot",
    "risk_category": "medium",
    "document_types": [
      "pan_card",
      "address_proof"
    ],
    "last_updated": "2024-01-01T09:00:00"
  }
}
